{
    "show_xp": {
        "scoreboard": "ShowXP",
        "value": {
            "range": 0,
            "inverted": true
        },
        "function": "micahcraft:commands/show_xp/trigger"
    },
    "show_deaths": {
        "scoreboard": "ShowDeaths",
        "value": {
            "range": 0,
            "inverted": true
        },
        "function": "micahcraft:commands/show_deaths/trigger"
    },
    "show_playtime": {
        "scoreboard": "ShowPlaytime",
        "value": {
            "range": 0,
            "inverted": true
        },
        "function": "micahcraft:commands/show_playtime/trigger"
    }
}