{
    "criteria": {
        "unlocked": {
            "trigger": "minecraft:item_used_on_block",
            "conditions": {
                "location": [
                    {
                        "condition": "match_tool",
                        "predicate": {
                            "items": "#shovels"
                        }
                    }
                ]
            }
        }
    },
    "rewards": {
        "function": "micahcraft:enchantments/veinmining/used/clear/scheduled/made_path"
    }
}